[1,["1aPQpAQvNEAoL4VZk6JvOj","16CtBIY5RIXJw3Z5BKf3yv@6c48a","7dj5uJT9FMn6OrOOx83tfK@f9941","7aQiWdaj5Af6ptRsDiYQ0l@f9941","6aaR4b0/pDt6jvIY+aOxsL@f9941","3aeR2cH8RMR6lL49bDffiz@f9941","ddGhwMzalD463dB8NYbuTt@f9941","16CtBIY5RIXJw3Z5BKf3yv@f9941","cblNL//1dDg614Rlq0OOqi@f9941"],["node","_spriteFrame","_font","_textureSource","root","_placeholderLabel","_textLabel","data","_parent"],[["cc.Sprite",["_sizeMode","_type","node","__prefab","_spriteFrame","_color"],1,1,4,6,5],["cc.Node",["_name","_layer","_components","_prefab","_parent","_children","_lpos"],1,9,4,1,2,5],["cc.Label",["_string","_actualFontSize","_fontSize","_isSystemFontUsed","_cacheMode","_overflow","_enableWrapText","_lineHeight","node","__prefab","_font","_color"],-5,1,4,6,5],["cc.Node",["_name","_layer","_active","_parent","_components","_prefab","_lpos"],0,1,12,4,5],["cc.UITransform",["node","__prefab","_contentSize","_anchorPoint"],3,1,4,5,5],["cc.Widget",["_alignFlags","_originalWidth","_originalHeight","node","__prefab"],0,1,4],"cc.SpriteFrame",["cc.Prefab",["_name"],2],["cc.CompPrefabInfo",["fileId"],2],["cc.PrefabInfo",["fileId","instance","targetOverrides","nestedPrefabInstanceRoots","root","asset"],-1,1,1],["cc.BlockInputEvents",["node","__prefab"],3,1,4],["cc.EditBox",["_inputMode","_maxLength","node","__prefab","_textLabel","_placeholderLabel"],1,1,4,1,1],["cc.Button",["node","__prefab"],3,1,4]],[[8,0,2],[9,0,1,2,3,4,5,5],[4,0,1,2,1],[1,0,1,4,5,2,3,6,3],[1,0,1,4,2,3,3],[1,0,1,4,2,3,6,3],[0,0,2,3,4,2],[1,0,1,5,2,3,3],[4,0,1,2,3,1],[0,2,3,4,1],[10,0,1,1],[5,0,1,2,3,4,4],[2,0,1,2,3,4,8,9,10,6],[7,0,2],[3,0,2,1,3,4,5,6,4],[3,0,1,3,4,5,6,3],[0,1,0,2,3,4,3],[0,1,0,2,3,3],[0,0,2,3,5,4,2],[11,0,1,2,3,4,5,3],[5,0,1,3,4,3],[12,0,1,1],[2,0,1,2,3,4,8,9,11,10,6],[2,0,1,2,5,6,3,8,9,7],[2,0,1,2,7,5,6,3,4,8,9,11,9]],[[[{"name":"input","rect":{"x":3,"y":3,"width":341,"height":62},"offset":{"x":0,"y":0},"originalSize":{"width":347,"height":68},"rotated":false,"capInsets":[0,0,0,0],"vertices":{"rawPosition":[-170.5,-31,0,170.5,-31,0,-170.5,31,0,170.5,31,0],"indexes":[0,1,2,2,1,3],"uv":[3,65,344,65,3,3,344,3],"nuv":[0.008645533141210375,0.04411764705882353,0.9913544668587896,0.04411764705882353,0.008645533141210375,0.9558823529411765,0.9913544668587896,0.9558823529411765],"minPos":{"x":-170.5,"y":-31,"z":0},"maxPos":{"x":170.5,"y":31,"z":0}},"packable":true,"pixelsToUnit":100,"pivot":{"x":0.5,"y":0.5},"meshType":0}],[6],0,[0],[3],[1]],[[[13,"remarkView"],[7,"remarkView",33554432,[-3,-4,-5,-6,-7,-8,-9],[[2,-2,[0,"0cE8GA8ihITafc72x8FEGl"],[5,750,1334]]],[1,"2fO9z+tytIlI1UDprqXSQn",null,null,null,-1,0]],[3,"bg",33554432,1,[-13,-14],[[2,-10,[0,"a5X2O/6V5AI7MhRWPcGTUZ"],[5,648,506]],[16,1,0,-11,[0,"9a1YSq4IFOB6zX4Rc4DiI4"],3],[10,-12,[0,"1cr0DSohlB4qrU1PwXD841"]]],[1,"e2zW3iyw5LUrY+ehTEfivI",null,null,null,1,0],[1,0,-27.552,0]],[7,"EditBox",33554432,[-20,-21],[[2,-15,[0,"ccv7oEg1BPKoB+njSQtfWp"],[5,340,62]],[17,1,0,-16,[0,"c8s3+XwuRIV5EGKAEE5N7J"]],[19,6,8,-19,[0,"e6szI4wM5OzaN+9gJXwLby"],-18,-17]],[1,"48TUwkZf1M8Yd/i0aG7Ewz",null,null,null,1,0]],[4,"SpriteSplash",33554432,1,[[2,-22,[0,"cc4B0O2X5LIL7rKEZuXCTE"],[5,750,1334]],[18,0,-23,[0,"b314rKiC5E4pDyDEJpv25p"],[4,2516582400],0],[11,45,100,100,-24,[0,"ebTXaJaIZOiZ/GrwMM75YA"]],[10,-25,[0,"15XEkiIolCdqyIil3PbOCn"]]],[1,"94zZrvaFRD8KDrV6VumOwW",null,null,null,1,0]],[4,"alert_bg2",33554432,2,[[2,-26,[0,"3fLhHGs1xINoT3SiqIJuka"],[5,648,506]],[6,0,-27,[0,"c6knxgyqxH5rCkfLyTtLwt"],1],[11,45,435,182,-28,[0,"0dUhTmLYdDS54TwRqskqOj"]]],[1,"8du7vrC7RAnIXoFe1ooARL",null,null,null,1,0]],[5,"alert_bg_title",33554432,2,[[2,-29,[0,"e3KbqvBQhBgKM+ad/Bz8T4"],[5,648,73]],[6,0,-30,[0,"acyQ08gRdPzaomTvtNIrEZ"],2],[20,41,648,-31,[0,"05hx4bOZ9BHK2MhOKPwUD5"]]],[1,"86Ytomd19BS4VB/4rViDeC",null,null,null,1,0],[1,0,216.5,0]],[3,"btnClose",33554432,1,[-34],[[2,-32,[0,"c8egZZze1FxKsT+0q9SCAv"],[5,60,60]],[21,-33,[0,"09wz96uXxMNY4EgtDqzRlu"]]],[1,"beNNDAKTpGM5ulfwspGiEE",null,null,null,1,0],[1,280.022,189.116,0]],[3,"input",33554432,1,[3],[[2,-35,[0,"dazdzIiZFIqrUn26M5ism2"],[5,340,62]],[6,0,-36,[0,"39YTWcjO1OSL/e2OLcXpxf"],7]],[1,"f2s1tMKz9FKpsj03EGkNZv",null,null,null,1,0],[1,34.383,-9.662,0]],[3,"confirm",33554432,1,[-39],[[2,-37,[0,"e0SjofcjNK2IZHIXPNKhM0"],[5,183,69]],[9,-38,[0,"fbVPyG7mJLIorUeZRShZBw"],9]],[1,"e1WMrIcrNH66Zp8u5So76r",null,null,null,1,0],[1,0,-193.262,0]],[5,"title",33554432,1,[[2,-40,[0,"a6JyJ6RH1FQLHlnmPxU811"],[5,128,50.4]],[12,"玩家备注",32,32,false,1,-41,[0,"f0WeRQggtNgoOLpOvDh8QZ"],4]],[1,"20PNJEQthHHKKLu/0ZZ5SK",null,null,null,1,0],[1,0,192.006,0]],[4,"but_close",33554432,7,[[2,-42,[0,"e7q6xZHhFFIITOFMA4nqJL"],[5,31,32]],[9,-43,[0,"34Hle9e0dIdJaVQxHFdFW2"],5]],[1,"21feyokgVBf66H1cPPT2w3",null,null,null,1,0]],[5,"Label",33554432,1,[[2,-44,[0,"adP9xs7rlIerw5wrnz/i5r"],[5,72,50.4]],[12,"备注：",24,24,false,1,-45,[0,"39cYj3eppEeaINBsnj6Kfe"],6]],[1,"70uIXfvFZKx5mwOeYXjRgp",null,null,null,1,0],[1,-178.068,-9.461,0]],[14,"TEXT_LABEL",false,33554432,3,[[[8,-46,[0,"3073DwVqxMZaIu9dIP6+uz"],[5,338,62],[0,0,1]],-47],4,1],[1,"2bVj92ZHJHhJVxunyyix9p",null,null,null,1,0],[1,-168,31,0]],[15,"PLACEHOLDER_LABEL",33554432,3,[[[8,-48,[0,"42ZEVCB2dLnKKVowUxMx9s"],[5,338,62],[0,0,1]],-49],4,1],[1,"bbniQqGQhNLbgks+p93iob",null,null,null,1,0],[1,-168,31,0]],[4,"Label",33554432,9,[[2,-50,[0,"eftxDveBBC+IRjJ86zRdYZ"],[5,60,50.4]],[22,"确认",30,30,false,1,-51,[0,"8aNN3AmqJOJZhbQicwQqCp"],[4,4280236643],8]],[1,"88eI3OzyBE9LXqzouIsFzX",null,null,null,1,0]],[23,"",24,24,1,false,false,13,[0,"aaij9lW95KCL6ivFCyV/ky"]],[24,"请输入玩家备注",24,24,62,1,false,false,1,14,[0,"a8JGNzRKZAxKEIVf815AuF"],[4,4283919998]]],0,[0,4,1,0,0,1,0,-1,4,0,-2,2,0,-3,10,0,-4,7,0,-5,12,0,-6,8,0,-7,9,0,0,2,0,0,2,0,0,2,0,-1,5,0,-2,6,0,0,3,0,0,3,0,5,17,0,6,16,0,0,3,0,-1,13,0,-2,14,0,0,4,0,0,4,0,0,4,0,0,4,0,0,5,0,0,5,0,0,5,0,0,6,0,0,6,0,0,6,0,0,7,0,0,7,0,-1,11,0,0,8,0,0,8,0,0,9,0,0,9,0,-1,15,0,0,10,0,0,10,0,0,11,0,0,11,0,0,12,0,0,12,0,0,13,0,-2,16,0,0,14,0,-2,17,0,0,15,0,0,15,0,7,1,3,8,8,51],[0,0,0,0,0,0,0,0,0,0,16,17],[1,1,1,1,2,1,2,1,2,1,2,2],[2,3,4,5,0,6,0,7,0,8,0,0]]]]
